adsquery/__init__.py
adsquery/definitions.py
adsquery/query.py
adsquery-0.1.1.dist-info/DESCRIPTION.rst
adsquery-0.1.1.dist-info/METADATA
adsquery-0.1.1.dist-info/RECORD
adsquery-0.1.1.dist-info/WHEEL
adsquery-0.1.1.dist-info/entry_points.txt
adsquery-0.1.1.dist-info/metadata.json
adsquery-0.1.1.dist-info/top_level.txt
