Metadata-Version: 2.0
Name: adsquery
Version: 0.1.1
Summary: Query the ADS using python
Home-page: https://github.com/cphyc/adsquery
Author: cphyc (Corentin Cadiou)
Author-email: contact@cphyc.me
License: MIT
Platform: UNKNOWN
Requires-Dist: requests
Requires-Dist: ads
Requires-Dist: tqdm
Provides-Extra: clipboard
Requires-Dist: pyperclip; extra == 'clipboard'
